collect_face_data/__init__.py
collect_face_data/cli.py
collect_face_data/collect_data.py
collect_face_data-0.0.2.dist-info/LICENSE
collect_face_data-0.0.2.dist-info/METADATA
collect_face_data-0.0.2.dist-info/WHEEL
collect_face_data-0.0.2.dist-info/entry_points.txt
collect_face_data-0.0.2.dist-info/top_level.txt
collect_face_data-0.0.2.dist-info/RECORD
