Metadata-Version: 2.1
Name: collect-face-data
Version: 0.0.2
Summary: A Python package for collecting face data for face recognition.
Author-email: Le Tran Quang Huy <letranquanghuy0204@gmail.com>
Keywords: helloworld,cli,python
Requires-Python: >=3.8
License-File: LICENSE
Requires-Dist: mtcnn-opencv
Requires-Dist: opencv-python
Requires-Dist: scipy
